{
    "configurations": [
        {
            "name": "Win32",
            "includePath": [
                "${workspaceRoot}\\*",
                "C:\\BackedUp\\Arduino_apps\\libraries\\MillisTime",
                "C:\\Program Files (x86)\\Arduino\\tools\\**",
                "C:\\Users\\Tomek\\AppData\\Local\\Arduino15\\packages\\esp8266\\hardware\\esp8266\\2.7.1\\**",
                "C:\\Users\\Tomek\\AppData\\Local\\Arduino15\\packages\\esp8266\\tools\\**"
            ],
            "forcedInclude": [],
            "browse": {
                "limitSymbolsToIncludedHeaders": false,
                "path": [
                    "${workspaceRoot}\\*"
                ]
            },
            "intelliSenseMode": "msvc-x64",
            "compilerPath": "C:\\Program Files (x86)\\Arduino\\hardware\\tools\\avr\\bin\\avr-gcc.exe",
            "cStandard": "c11",
            "cppStandard": "c++17",
            "defines": [
                "USBCON",
                "C_CPP"
            ]
        }
    ],
    "version": 4
}